bloxfetch/__init__.py
bloxfetch/main.py
bloxfetch-0.2.dist-info/METADATA
bloxfetch-0.2.dist-info/WHEEL
bloxfetch-0.2.dist-info/top_level.txt
bloxfetch-0.2.dist-info/RECORD
