Metadata-Version: 2.1
Name: bloxfetch
Version: 0.2
Summary: A simple but advanced way for fetching roblox user info
Requires-Dist: requests
